benchmark/run.py
benchmark/timer.py
benchmark/__init__.py
benchmark/format.py
benchmark/benchmarks.py
benchmark/prepare.py
rayforce_py-0.5.6.dist-info/RECORD
rayforce_py-0.5.6.dist-info/WHEEL
rayforce_py-0.5.6.dist-info/entry_points.txt
rayforce_py-0.5.6.dist-info/top_level.txt
rayforce_py-0.5.6.dist-info/METADATA
rayforce_py-0.5.6.dist-info/licenses/LICENSE
tests/__init__.py
tests/test_ffi.py
tests/types/test_registry.py
tests/types/test_operators.py
tests/types/__init__.py
tests/types/test_null.py
tests/types/test_mixins.py
tests/types/test_fn.py
tests/types/scalars/__init__.py
tests/types/scalars/temporal/test_time.py
tests/types/scalars/temporal/test_timestamp.py
tests/types/scalars/temporal/__init__.py
tests/types/scalars/temporal/test_date.py
tests/types/scalars/other/test_guid.py
tests/types/scalars/other/test_boolean.py
tests/types/scalars/other/test_char.py
tests/types/scalars/other/__init__.py
tests/types/scalars/other/test_symbol.py
tests/types/scalars/numeric/test_unsigned.py
tests/types/scalars/numeric/__init__.py
tests/types/scalars/numeric/test_integer.py
tests/types/scalars/numeric/test_float.py
tests/types/table/test_misc.py
tests/types/table/test_insert.py
tests/types/table/test_select.py
tests/types/table/test_join.py
tests/types/table/__init__.py
tests/types/table/test_pivot.py
tests/types/table/test_upsert.py
tests/types/table/test_update.py
tests/types/table/test_order_by.py
tests/types/containers/test_list.py
tests/types/containers/test_string.py
tests/types/containers/__init__.py
tests/types/containers/test_vector.py
tests/types/containers/test_dict.py
tests/plugins/test_parquet.py
tests/plugins/test_polars.py
tests/plugins/__init__.py
tests/plugins/test_sql.py
tests/plugins/test_pandas.py
tests/plugins/test_raykx.py
tests/network/test_utils.py
tests/network/conftest.py
tests/network/__init__.py
tests/network/websocket/test_query_objects.py
tests/network/websocket/__init__.py
tests/network/websocket/test_server.py
tests/network/websocket/test_client.py
tests/network/tcp/test_query_objects.py
tests/network/tcp/__init__.py
tests/network/tcp/test_server.py
tests/network/tcp/test_client.py
tests/utils/__init__.py
