Metadata-Version: 2.4
Name: rayforce_py
Version: 0.5.6
Summary: Python bindings for RayforceDB
Author: Karim
License: MIT
Classifier: Development Status :: 4 - Beta
Classifier: Intended Audience :: Developers
Classifier: Intended Audience :: Financial and Insurance Industry
Classifier: Intended Audience :: Information Technology
Classifier: License :: OSI Approved :: MIT License
Classifier: Programming Language :: Python :: 3.11
Classifier: Programming Language :: Python :: 3.12
Classifier: Programming Language :: Python :: 3.13
Classifier: Programming Language :: Python :: 3.14
Classifier: Programming Language :: C
Requires-Python: >=3.11
License-File: LICENSE
Provides-Extra: pandas
Requires-Dist: pandas>=2.0.0; extra == "pandas"
Provides-Extra: polars
Requires-Dist: polars>=0.19.0; extra == "polars"
Provides-Extra: parquet
Requires-Dist: pyarrow>=10.0.0; extra == "parquet"
Provides-Extra: all
Requires-Dist: pandas>=2.0.0; extra == "all"
Requires-Dist: polars>=0.19.0; extra == "all"
Requires-Dist: pyarrow>=10.0.0; extra == "all"
Provides-Extra: dev
Requires-Dist: pytest>=7.0.0; extra == "dev"
Requires-Dist: pytest-cov>=4.0.0; extra == "dev"
Requires-Dist: coverage>=7.0.0; extra == "dev"
Requires-Dist: ruff>=0.1.0; extra == "dev"
Requires-Dist: mypy>=1.0.0; extra == "dev"
Requires-Dist: pandas>=2.0.0; extra == "dev"
Requires-Dist: polars>=0.19.0; extra == "dev"
Dynamic: license-file
Dynamic: requires-python
